[
    {
        "text": "॥ ॐ श्री परमात्मने नमः ॥",
        "index": 0,
        "shloka_num": null
    },
    {
        "text": "॥ अथ श्रीमद्भगवद्गीता ॥",
        "index": 1,
        "shloka_num": null
    },
    {
        "text": "अथ चतुर्दशोऽध्यायः ।   गुणत्रयविभागयोगः",
        "index": 2,
        "shloka_num": null
    },
    {
        "text": "श्रीभगवानुवाच ।",
        "index": 3,
        "shloka_num": null
    },
    {
        "text": "परं भूयः प्रवक्ष्यामि ज्ञानानां ज्ञानमुत्तमम् ।\nयज्ज्ञात्वा मुनयः सर्वे परां सिद्धिमितो गताः ॥१४-१॥",
        "index": 4,
        "shloka_num": 1
    },
    {
        "text": "इदं ज्ञानमुपाश्रित्य मम साधर्म्यमागताः ।\nसर्गेऽपि नोपजायन्ते प्रलये न व्यथन्ति च ॥१४-२॥",
        "index": 5,
        "shloka_num": 2
    },
    {
        "text": "मम योनिर्महद् ब्रह्म तस्मिन्गर्भं दधाम्यहम् ।\nसम्भवः सर्वभूतानां ततो भवति भारत ॥१४-३॥",
        "index": 6,
        "shloka_num": 3
    },
    {
        "text": "सर्वयोनिषु कौन्तेय मूर्तयः सम्भवन्ति याः ।\nतासां ब्रह्म महद्योनिरहं बीजप्रदः पिता ॥१४-४॥",
        "index": 7,
        "shloka_num": 4
    },
    {
        "text": "सत्त्वं रजस्तम इति गुणाः प्रकृतिसम्भवाः ।\nनिबध्नन्ति महाबाहो देहे देहिनमव्ययम् ॥१४-५॥",
        "index": 8,
        "shloka_num": 5
    },
    {
        "text": "तत्र सत्त्वं निर्मलत्वात्प्रकाशकमनामयम् ।\nसुखसङ्गेन बध्नाति ज्ञानसङ्गेन चानघ ॥१४-६॥",
        "index": 9,
        "shloka_num": 6
    },
    {
        "text": "रजो रागात्मकं विद्धि तृष्णासङ्गसमुद्भवम् ।\nतन्निबध्नाति कौन्तेय कर्मसङ्गेन देहिनम् ॥१४-७॥",
        "index": 10,
        "shloka_num": 7
    },
    {
        "text": "तमस्त्वज्ञानजं विद्धि मोहनं सर्वदेहिनाम् ।\nप्रमादालस्यनिद्राभिस्तन्निबध्नाति भारत ॥१४-८॥",
        "index": 11,
        "shloka_num": 8
    },
    {
        "text": "सत्त्वं सुखे सञ्जयति रजः कर्मणि भारत ।\nज्ञानमावृत्य तु तमः प्रमादे सञ्जयत्युत ॥१४-९॥",
        "index": 12,
        "shloka_num": 9
    },
    {
        "text": "रजस्तमश्चाभिभूय सत्त्वं भवति भारत ।\nरजः सत्त्वं तमश्चैव तमः सत्त्वं रजस्तथा ॥१४-१०॥",
        "index": 13,
        "shloka_num": 10
    },
    {
        "text": "सर्वद्वारेषु देहेऽस्मिन्प्रकाश उपजायते ।\nज्ञानं यदा तदा विद्याद्विवृद्धं सत्त्वमित्युत ॥१४-११॥",
        "index": 14,
        "shloka_num": 11
    },
    {
        "text": "लोभः प्रवृत्तिरारम्भः कर्मणामशमः स्पृहा ।\nरजस्येतानि जायन्ते विवृद्धे भरतर्षभ ॥१४-१२॥",
        "index": 15,
        "shloka_num": 12
    },
    {
        "text": "अप्रकाशोऽप्रवृत्तिश्च प्रमादो मोह एव च ।\nतमस्येतानि जायन्ते विवृद्धे कुरुनन्दन ॥१४-१३॥",
        "index": 16,
        "shloka_num": 13
    },
    {
        "text": "यदा सत्त्वे प्रवृद्धे तु प्रलयं याति देहभृत् ।\nतदोत्तमविदां लोकानमलान्प्रतिपद्यते ॥१४-१४॥",
        "index": 17,
        "shloka_num": 14
    },
    {
        "text": "रजसि प्रलयं गत्वा कर्मसङ्गिषु जायते ।\nतथा प्रलीनस्तमसि मूढयोनिषु जायते ॥१४-१५॥",
        "index": 18,
        "shloka_num": 15
    },
    {
        "text": "कर्मणः सुकृतस्याहुः सात्त्विकं निर्मलं फलम् ।\nरजसस्तु फलं दुःखमज्ञानं तमसः फलम् ॥१४-१६॥",
        "index": 19,
        "shloka_num": 16
    },
    {
        "text": "सत्त्वात्सञ्जायते ज्ञानं रजसो लोभ एव च ।\nप्रमादमोहौ तमसो भवतोऽज्ञानमेव च ॥१४-१७॥",
        "index": 20,
        "shloka_num": 17
    },
    {
        "text": "ऊर्ध्वं गच्छन्ति सत्त्वस्था मध्ये तिष्ठन्ति राजसाः ।\nजघन्यगुणवृत्तिस्था अधो गच्छन्ति तामसाः ॥१४-१८॥",
        "index": 21,
        "shloka_num": 18
    },
    {
        "text": "नान्यं गुणेभ्यः कर्तारं यदा द्रष्टानुपश्यति ।\nगुणेभ्यश्च परं वेत्ति मद्भावं सोऽधिगच्छति ॥१४-१९॥",
        "index": 22,
        "shloka_num": 19
    },
    {
        "text": "गुणानेतानतीत्य त्रीन्देही देहसमुद्भवान् ।\nजन्ममृत्युजरादुःखैर्विमुक्तोऽमृतमश्नुते ॥१४-२०॥",
        "index": 23,
        "shloka_num": 20
    },
    {
        "text": "अर्जुन उवाच ।",
        "index": 24,
        "shloka_num": null
    },
    {
        "text": "कैर्लिङ्गैस्त्रीन्गुणानेतानतीतो भवति प्रभो ।\nकिमाचारः कथं चैतांस्त्रीन्गुणानतिवर्तते ॥१४-२१॥",
        "index": 25,
        "shloka_num": 21
    },
    {
        "text": "श्रीभगवानुवाच ।",
        "index": 26,
        "shloka_num": null
    },
    {
        "text": "प्रकाशं च प्रवृत्तिं च मोहमेव च पाण्डव ।\nन द्वेष्टि सम्प्रवृत्तानि न निवृत्तानि काङ्क्षति ॥१४-२२॥",
        "index": 27,
        "shloka_num": 22
    },
    {
        "text": "उदासीनवदासीनो गुणैर्यो न विचाल्यते ।\nगुणा वर्तन्त इत्येवं योऽवतिष्ठति नेङ्गते ॥१४-२३॥",
        "index": 28,
        "shloka_num": 23
    },
    {
        "text": "समदुःखसुखः स्वस्थः समलोष्टाश्मकाञ्चनः ।\nतुल्यप्रियाप्रियो धीरस्तुल्यनिन्दात्मसंस्तुतिः ॥१४-२४॥",
        "index": 29,
        "shloka_num": 24
    },
    {
        "text": "मानापमानयोस्तुल्यस्तुल्यो मित्रारिपक्षयोः ।\nसर्वारम्भपरित्यागी गुणातीतः स उच्यते ॥१४-२५॥",
        "index": 30,
        "shloka_num": 25
    },
    {
        "text": "मां च योऽव्यभिचारेण भक्तियोगेन सेवते ।\nस गुणान्समतीत्यैतान्ब्रह्मभूयाय कल्पते ॥१४-२६॥",
        "index": 31,
        "shloka_num": 26
    },
    {
        "text": "ब्रह्मणो हि प्रतिष्ठाहममृतस्याव्ययस्य च ।\nशाश्वतस्य च धर्मस्य सुखस्यैकान्तिकस्य च ॥१४-२७॥",
        "index": 32,
        "shloka_num": 27
    },
    {
        "text": "ॐ तत्सदिति श्रीमद्भगवद्गीतासूपनिषत्सु\nब्रह्मविद्यायां योगशास्त्रे श्रीकृष्णार्जुनसंवादे\nगुणत्रयविभागयोगो नाम चतुर्दशोऽध्यायः ॥१४॥",
        "index": 33,
        "shloka_num": null
    }
]