{
    "range": [
        [
            70016,
            70111
        ]
    ],
    "sa": 0,
    "a": {
        "a": [
            "\ud804\udd83",
            "",
            "aiu1",
            0
        ],
        "a1": [
            "\ud804\udd83\ud804\uddcb",
            "\ud804\uddcb",
            "",
            0
        ],
        "ai": [
            "\ud804\udd8e",
            "\ud804\uddbd",
            "",
            0
        ],
        "au": [
            "\ud804\udd90",
            "\ud804\uddbf",
            "",
            0
        ],
        "aa": [
            "\ud804\udd84",
            "\ud804\uddb3",
            "",
            0
        ]
    },
    "A": {
        "A": [
            "\ud804\udd84",
            "\ud804\uddb3",
            "U1",
            0
        ],
        "A1": [
            "\ud804\udd83\ud804\uddcb\ud804\uddb3",
            "\ud804\uddcb\ud804\uddb3",
            "",
            0
        ],
        "AU": [
            "\ud804\udd84\ud804\udd88",
            "M",
            2
        ],
        "AUM": [
            "\ud804\uddc4",
            "12",
            2
        ],
        "AUM1": [
            "\u0950",
            "",
            2
        ],
        "AUM2": [
            "\u5350",
            "",
            2
        ]
    },
    "i": {
        "i": [
            "\ud804\udd85",
            "\ud804\uddb4",
            "i",
            0
        ],
        "ii": [
            "\ud804\udd86",
            "\ud804\uddb5",
            "",
            0
        ]
    },
    "I": {
        "I": [
            "\ud804\udd86",
            "\ud804\uddb5",
            "",
            0
        ]
    },
    "u": {
        "u": [
            "\ud804\udd87",
            "\ud804\uddb6",
            "u1",
            0
        ],
        "u1": [
            "\ud804\udd83\ud804\uddcb\ud804\uddb6",
            "\ud804\uddcb\ud804\uddb6",
            "",
            0
        ],
        "uu": [
            "\ud804\udd88",
            "\ud804\uddb7",
            "",
            0
        ]
    },
    "U": {
        "U": [
            "\ud804\udd88",
            "\ud804\uddb7",
            "1",
            0
        ],
        "U1": [
            "\ud804\udd83\ud804\uddcb\ud804\uddb7",
            "\ud804\uddcb\ud804\uddb7",
            "",
            0
        ]
    },
    "e": {
        "e": [
            "\ud804\udd8d\ud804\uddcc",
            "\ud804\uddbc\ud804\uddcc",
            "e21",
            0
        ],
        "ee": [
            "\ud804\udd86",
            "\ud804\uddb5",
            "",
            0
        ],
        "e2": [
            "\ud804\udd8d",
            "\ud804\uddbc",
            "",
            0
        ],
        "e1": [
            "\ud804\udd8e",
            "\ud804\uddbd",
            "",
            0
        ]
    },
    "E": {
        "E": [
            "\ud804\udd8d",
            "\ud804\uddbc",
            "",
            0
        ]
    },
    "o": {
        "o": [
            "\ud804\udd8f\ud804\uddcc",
            "\ud804\uddbe\ud804\uddcc",
            "o21",
            0
        ],
        "oo": [
            "\ud804\udd88",
            "\ud804\uddb7",
            "",
            0
        ],
        "o2": [
            "\ud804\udd8f",
            "\ud804\uddbe",
            "",
            0
        ],
        "o1": [
            "\ud804\udd90",
            "\ud804\uddbf",
            "",
            0
        ]
    },
    "O": {
        "O": [
            "\ud804\udd8f",
            "\ud804\uddbe",
            "",
            0
        ]
    },
    "R": {
        "R": [
            "\ud804\udd89",
            "\ud804\uddb8",
            "R",
            0
        ],
        "RR": [
            "\ud804\udd8a",
            "\ud804\uddb9",
            "",
            0
        ]
    },
    "k": {
        "k": [
            "\ud804\udd91",
            "hz",
            1
        ],
        "kh": [
            "\ud804\udd92",
            "z",
            1
        ],
        "kz": [
            "\ud804\udd91\ud804\uddca",
            "",
            1
        ],
        "khz": [
            "\ud804\udd92\ud804\uddca",
            "",
            1
        ]
    },
    "g": {
        "g": [
            "\ud804\udd93",
            "hz",
            1
        ],
        "gh": [
            "\ud804\udd94",
            "",
            1
        ],
        "gz": [
            "\ud804\udd93\ud804\uddca",
            "",
            1
        ]
    },
    "G": {
        "G": [
            "\ud804\udd95",
            "1",
            1
        ],
        "G1": [
            "\ud804\udd81",
            "",
            2
        ]
    },
    "c": {
        "c": [
            "c",
            "h",
            2
        ],
        "ch": [
            "\ud804\udd96",
            "hz",
            1
        ],
        "chh": [
            "\ud804\udd97",
            "z",
            1
        ],
        "chz": [
            "\ud804\udd96\ud804\uddca",
            "",
            1
        ],
        "chhz": [
            "\ud804\udd97\ud804\uddca",
            "",
            1
        ]
    },
    "C": {
        "C": [
            "\ud804\udd96",
            "hz",
            1
        ],
        "Ch": [
            "\ud804\udd97",
            "z",
            1
        ],
        "Cz": [
            "\ud804\udd96\ud804\uddca",
            "",
            1
        ],
        "Chz": [
            "\ud804\udd97\ud804\uddca",
            "",
            1
        ]
    },
    "j": {
        "j": [
            "\ud804\udd98",
            "hz",
            1
        ],
        "jh": [
            "\ud804\udd99",
            "",
            1
        ],
        "jz": [
            "\ud804\udd98\ud804\uddca",
            "",
            1
        ]
    },
    "J": {
        "J": [
            "\ud804\udd9a",
            "1",
            1
        ],
        "J1": [
            "\ud804\udd81",
            "",
            2
        ]
    },
    "Y": {
        "Y": [
            "\ud804\udd9a",
            "1",
            1
        ],
        "Y1": [
            "\ud804\udd81",
            "",
            2
        ]
    },
    "T": {
        "T": [
            "\ud804\udd9b",
            "h",
            1
        ],
        "Th": [
            "\ud804\udd9c",
            "",
            1
        ]
    },
    "D": {
        "D": [
            "\ud804\udd9d",
            "hz",
            1
        ],
        "Dh": [
            "\ud804\udd9e",
            "z",
            1
        ],
        "Dz": [
            "\ud804\udd9d\ud804\uddca",
            "",
            1
        ],
        "Dhz": [
            "\ud804\udd9e\ud804\uddca",
            "",
            1
        ]
    },
    "N": {
        "N": [
            "\ud804\udd9f",
            "1",
            1
        ],
        "N1": [
            "\ud804\udd81",
            "",
            2
        ]
    },
    "t": {
        "t": [
            "\ud804\udda0",
            "h1",
            1
        ],
        "th": [
            "\ud804\udda1",
            "1",
            1
        ],
        "t1": [
            "\ud804\udd9b",
            "",
            1
        ],
        "th1": [
            "\ud804\udd9c",
            "",
            1
        ]
    },
    "d": {
        "d": [
            "\ud804\udda2",
            "h12",
            1
        ],
        "dh": [
            "\ud804\udda3",
            "12",
            1
        ],
        "d1": [
            "\ud804\udd9d",
            "",
            1
        ],
        "dh1": [
            "\ud804\udd9e",
            "",
            1
        ],
        "d2": [
            "\ud804\udd9d\ud804\uddca",
            "",
            1
        ],
        "dh2": [
            "\ud804\udd9e\ud804\uddca",
            "",
            1
        ]
    },
    "n": {
        "n": [
            "\ud804\udda4",
            "z1234",
            1
        ],
        "nz": [
            "\ud804\udda4\ud804\uddca",
            "",
            1
        ],
        "n1": [
            "\ud804\udd81",
            "",
            2
        ],
        "n2": [
            "\ud804\udd9f",
            "",
            1
        ],
        "n3": [
            "\ud804\udd95",
            "",
            1
        ],
        "n4": [
            "\ud804\udd9a",
            "",
            1
        ]
    },
    "p": {
        "p": [
            "\ud804\udda5",
            "h",
            1
        ],
        "ph": [
            "\ud804\udda6",
            "z",
            1
        ],
        "phz": [
            "\ud804\udda6\ud804\uddca",
            "",
            1
        ]
    },
    "f": {
        "f": [
            "\ud804\udda6",
            "z",
            1
        ],
        "fz": [
            "\ud804\udda6\ud804\uddca",
            "",
            1
        ]
    },
    "b": {
        "b": [
            "\ud804\udda7",
            "h",
            1
        ],
        "bh": [
            "\ud804\udda8",
            "",
            1
        ]
    },
    "m": {
        "m": [
            "\ud804\udda9",
            "1",
            1
        ],
        "m1": [
            "\ud804\udd81",
            "m",
            2
        ],
        "m1m": [
            "\ud804\udd80",
            "",
            2
        ]
    },
    "x": {
        "x": [
            "\ud804\udd91\ud804\uddc0\ud804\uddb0",
            "",
            1
        ]
    },
    "y": {
        "y": [
            "\ud804\uddaa",
            "z",
            1
        ],
        "yz": [
            "\ud804\uddaa\ud804\uddca",
            "",
            1
        ]
    },
    "r": {
        "r": [
            "\ud804\uddab",
            "z13",
            1
        ],
        "rz": [
            "\ud804\uddab\ud804\uddca",
            "",
            1
        ],
        "r1": [
            "\ud804\udd9d\ud804\uddca",
            "h",
            1
        ],
        "r1h": [
            "\ud804\udd9e\ud804\uddca",
            "",
            1
        ],
        "r3": [
            "\ud804\udd89",
            "\ud804\uddb8",
            "r",
            0
        ],
        "r3r": [
            "\ud804\udd8a",
            "\ud804\uddb9",
            "",
            0
        ]
    },
    "l": {
        "l": [
            "\ud804\uddac",
            "1",
            1
        ],
        "l1": [
            "\ud804\uddad",
            "",
            1
        ]
    },
    "L": {
        "L": [
            "\ud804\uddad",
            "Rz",
            1
        ],
        "Lz": [
            "\ud804\uddad\ud804\uddca",
            "",
            1
        ],
        "LR": [
            "\ud804\udd8b",
            "\ud804\uddba",
            "R",
            0
        ],
        "LRR": [
            "\ud804\udd8c",
            "\ud804\uddbb",
            "",
            0
        ]
    },
    "v": {
        "v": [
            "\ud804\uddae",
            "",
            1
        ]
    },
    "w": {
        "w": [
            "\ud804\uddae",
            "",
            1
        ]
    },
    "h": {
        "h": [
            "\ud804\uddb2",
            "1",
            1
        ],
        "h1": [
            "\ud804\udd82",
            "",
            2
        ]
    },
    "s": {
        "s": [
            "\ud804\uddb1",
            "h",
            1
        ],
        "sh": [
            "\ud804\uddaf",
            "h",
            1
        ],
        "shh": [
            "\ud804\uddb0",
            "",
            1
        ]
    },
    "S": {
        "S": [
            "S",
            "hW",
            2
        ],
        "Sh": [
            "\ud804\uddb0",
            "",
            1
        ],
        "SW": [
            "SW",
            "S",
            2
        ],
        "SWS": [
            "\u5350",
            "",
            2
        ]
    },
    "z": {
        "z": [
            "\ud804\udd98\ud804\uddca",
            "",
            1
        ]
    },
    "M": {
        "M": [
            "\ud804\udd81",
            "M1",
            2
        ],
        "MM": [
            "\ud804\udd80",
            "",
            2
        ],
        "M1": [
            "\ud804\udd80",
            "",
            2
        ]
    },
    "H": {
        "H": [
            "\ud804\udd82",
            "",
            2
        ]
    },
    "Q": {
        "Q": [
            "\ud804\uddc6",
            "Q",
            2
        ],
        "QQ": [
            "\ud804\uddc1",
            "",
            2
        ]
    },
    "'": {
        "'": [
            "'",
            "'",
            2
        ],
        "''": [
            "\ud804\uddc1",
            "",
            2
        ]
    },
    "$": {
        "$": [
            "$",
            "$",
            2
        ],
        "$$": [
            "\u20b9",
            "",
            2
        ]
    },
    "q": {
        "q": [
            "q",
            "q.",
            2
        ],
        "qq": [
            "\ud804\uddc0",
            "",
            2
        ],
        "q.": [
            ".",
            "",
            2
        ]
    },
    ".": {
        ".": [
            "\ud804\uddc5",
            "x.1234567890aAiIuUeEoORzkRLqn",
            2
        ],
        "..": [
            "\ud804\uddc6",
            "",
            2
        ],
        ".z": [
            "\ud804\uddca",
            "",
            2
        ],
        ".k": [
            "\ud804\uddda",
            "",
            2
        ],
        ".0": [
            "\ud804\uddd0",
            "",
            2
        ],
        ".1": [
            "\ud804\uddd1",
            "",
            2
        ],
        ".2": [
            "\ud804\uddd2",
            "",
            2
        ],
        ".3": [
            "\ud804\uddd3",
            "",
            2
        ],
        ".4": [
            "\ud804\uddd4",
            "",
            2
        ],
        ".5": [
            "\ud804\uddd5",
            "",
            2
        ],
        ".6": [
            "\ud804\uddd6",
            "",
            2
        ],
        ".7": [
            "\ud804\uddd7",
            "",
            2
        ],
        ".8": [
            "\ud804\uddd8",
            "",
            2
        ],
        ".9": [
            "\ud804\uddd9",
            "",
            2
        ],
        ".a": [
            "",
            "aiu1",
            2
        ],
        ".a1": [
            "\ud804\uddcb",
            "",
            2
        ],
        ".A": [
            "\ud804\uddb3",
            "1",
            2
        ],
        ".A1": [
            "\ud804\uddcb\ud804\uddb3",
            "",
            2
        ],
        ".i": [
            "\ud804\uddb4",
            "i",
            2
        ],
        ".u": [
            "\ud804\uddb6",
            "u1",
            2
        ],
        ".u1": [
            "\ud804\uddcb\ud804\uddb6",
            "",
            2
        ],
        ".U": [
            "\ud804\uddb7",
            "1",
            2
        ],
        ".U1": [
            "\ud804\uddcb\ud804\uddb7",
            "",
            2
        ],
        ".e": [
            "\ud804\uddbc\ud804\uddcc",
            "e",
            2
        ],
        ".o": [
            "\ud804\uddbe\ud804\uddcc",
            "o",
            2
        ],
        ".L": [
            ".L",
            "R",
            2
        ],
        ".LR": [
            "\ud804\uddba",
            "R",
            2
        ],
        ".R": [
            "\ud804\uddb8",
            "R",
            2
        ],
        ".q": [
            "\u200c",
            "1",
            2
        ],
        ".q1": [
            "\u200d",
            "",
            2
        ],
        ".n": [
            ".n",
            "234",
            2
        ],
        ".n2": [
            "\u00b2",
            "",
            2
        ],
        ".n3": [
            "\u00b3",
            "",
            2
        ],
        ".n4": [
            "\u2074",
            "",
            2
        ],
        ".aa": [
            "\ud804\uddb3",
            "",
            2
        ],
        ".I": [
            "\ud804\uddb5",
            "",
            2
        ],
        ".ii": [
            "\ud804\uddb5",
            "",
            2
        ],
        ".ee": [
            "\ud804\uddb5",
            "",
            2
        ],
        ".uu": [
            "\ud804\uddb7",
            "",
            2
        ],
        ".oo": [
            "\ud804\uddb7",
            "",
            2
        ],
        ".E": [
            "\ud804\uddbc",
            "",
            2
        ],
        ".O": [
            "\ud804\uddbe",
            "",
            2
        ],
        ".ai": [
            "\ud804\uddbd",
            "",
            2
        ],
        ".au": [
            "\ud804\uddbf",
            "",
            2
        ],
        ".RR": [
            "\ud804\uddb9",
            "",
            2
        ],
        ".LRR": [
            "\ud804\uddbb",
            "",
            2
        ],
        ".x": [
            "\ud804\uddc0",
            "",
            2
        ]
    },
    "#": {
        "#": [
            "#",
            "as",
            2
        ],
        "#a": [
            "#a",
            "n",
            2
        ],
        "#an": [
            "\u2193",
            "",
            2
        ],
        "#s": [
            "\u2191",
            "s",
            2
        ],
        "#ss": [
            "\u2191\u2191",
            "s",
            2
        ],
        "#sss": [
            "\u2191\u2191\u2191",
            "",
            2
        ]
    },
    "antar": {
        ".": [
            "q.",
            2
        ],
        "\u0950": [
            "AUM",
            2
        ],
        "\u200d": [
            ".q1",
            2
        ],
        "\u20b9": [
            "$$",
            2
        ],
        "\u2191": [
            "#s",
            2,
            "\u2191"
        ],
        "\u2191\u2191": [
            "#ss",
            2,
            "\u2191"
        ],
        "\u2191\u2191\u2191": [
            "#sss",
            2
        ],
        "\u2193": [
            "#an",
            2
        ],
        "\ud804\udd80": [
            "MM",
            2
        ],
        "\ud804\udd81": [
            "M",
            2
        ],
        "\ud804\udd82": [
            "H",
            2
        ],
        "\ud804\udd83": [
            "a",
            2,
            "\ud804\uddcb"
        ],
        "\ud804\udd83\ud804\uddcb": [
            "a1",
            2,
            "\ud804\uddb3\ud804\uddb6\ud804\uddb7"
        ],
        "\ud804\udd83\ud804\uddcb\ud804\uddb3": [
            "A1",
            2
        ],
        "\ud804\udd83\ud804\uddcb\ud804\uddb6": [
            "u1",
            2
        ],
        "\ud804\udd83\ud804\uddcb\ud804\uddb7": [
            "U1",
            2
        ],
        "\ud804\udd84": [
            "A",
            2
        ],
        "\ud804\udd85": [
            "i",
            2
        ],
        "\ud804\udd86": [
            "I",
            2
        ],
        "\ud804\udd87": [
            "u",
            2
        ],
        "\ud804\udd88": [
            "U",
            2
        ],
        "\ud804\udd89": [
            "R",
            2
        ],
        "\ud804\udd8a": [
            "RR",
            2
        ],
        "\ud804\udd8b": [
            "LR",
            2
        ],
        "\ud804\udd8c": [
            "LRR",
            2
        ],
        "\ud804\udd8d": [
            "E",
            2,
            "\ud804\uddcc"
        ],
        "\ud804\udd8d\ud804\uddcc": [
            "e",
            2
        ],
        "\ud804\udd8e": [
            "ai",
            2
        ],
        "\ud804\udd8f": [
            "O",
            2,
            "\ud804\uddcc"
        ],
        "\ud804\udd8f\ud804\uddcc": [
            "o",
            2
        ],
        "\ud804\udd90": [
            "au",
            2
        ],
        "\ud804\udd91": [
            "k",
            1,
            "\ud804\uddca"
        ],
        "\ud804\udd91\ud804\uddca": [
            "kz",
            1
        ],
        "\ud804\udd92": [
            "kh",
            1,
            "\ud804\uddca"
        ],
        "\ud804\udd92\ud804\uddca": [
            "khz",
            1
        ],
        "\ud804\udd93": [
            "g",
            1,
            "\ud804\uddca"
        ],
        "\ud804\udd93\ud804\uddca": [
            "gz",
            1
        ],
        "\ud804\udd94": [
            "gh",
            1
        ],
        "\ud804\udd95": [
            "G",
            1
        ],
        "\ud804\udd96": [
            "ch",
            1,
            "\ud804\uddca"
        ],
        "\ud804\udd96\ud804\uddca": [
            "Cz",
            1
        ],
        "\ud804\udd97": [
            "chh",
            1,
            "\ud804\uddca"
        ],
        "\ud804\udd97\ud804\uddca": [
            "Chz",
            1
        ],
        "\ud804\udd98": [
            "j",
            1,
            "\ud804\uddca"
        ],
        "\ud804\udd98\ud804\uddca": [
            "jz",
            1
        ],
        "\ud804\udd99": [
            "jh",
            1
        ],
        "\ud804\udd9a": [
            "Y",
            1
        ],
        "\ud804\udd9b": [
            "T",
            1
        ],
        "\ud804\udd9c": [
            "Th",
            1
        ],
        "\ud804\udd9d": [
            "D",
            1,
            "\ud804\uddca"
        ],
        "\ud804\udd9d\ud804\uddca": [
            "Dz",
            1
        ],
        "\ud804\udd9e": [
            "Dh",
            1,
            "\ud804\uddca"
        ],
        "\ud804\udd9e\ud804\uddca": [
            "Dhz",
            1
        ],
        "\ud804\udd9f": [
            "N",
            1
        ],
        "\ud804\udda0": [
            "t",
            1
        ],
        "\ud804\udda1": [
            "th",
            1
        ],
        "\ud804\udda2": [
            "d",
            1
        ],
        "\ud804\udda3": [
            "dh",
            1
        ],
        "\ud804\udda4": [
            "n",
            1,
            "\ud804\uddca"
        ],
        "\ud804\udda4\ud804\uddca": [
            "nz",
            1
        ],
        "\ud804\udda5": [
            "p",
            1
        ],
        "\ud804\udda6": [
            "ph",
            1,
            "\ud804\uddca"
        ],
        "\ud804\udda6\ud804\uddca": [
            "phz",
            1
        ],
        "\ud804\udda7": [
            "b",
            1
        ],
        "\ud804\udda8": [
            "bh",
            1
        ],
        "\ud804\udda9": [
            "m",
            1
        ],
        "\ud804\uddaa": [
            "y",
            1,
            "\ud804\uddca"
        ],
        "\ud804\uddaa\ud804\uddca": [
            "yz",
            1
        ],
        "\ud804\uddab": [
            "r",
            1,
            "\ud804\uddca"
        ],
        "\ud804\uddab\ud804\uddca": [
            "rz",
            1
        ],
        "\ud804\uddac": [
            "l",
            1
        ],
        "\ud804\uddad": [
            "L",
            1,
            "\ud804\uddca"
        ],
        "\ud804\uddad\ud804\uddca": [
            "Lz",
            1
        ],
        "\ud804\uddae": [
            "v",
            1
        ],
        "\ud804\uddaf": [
            "sh",
            1
        ],
        "\ud804\uddb0": [
            "Sh",
            1
        ],
        "\ud804\uddb1": [
            "s",
            1
        ],
        "\ud804\uddb2": [
            "h",
            1
        ],
        "\ud804\uddb3": [
            "A",
            0
        ],
        "\ud804\uddb4": [
            "i",
            0
        ],
        "\ud804\uddb5": [
            "I",
            0
        ],
        "\ud804\uddb6": [
            "u",
            0
        ],
        "\ud804\uddb7": [
            "U",
            0
        ],
        "\ud804\uddb8": [
            "R",
            0
        ],
        "\ud804\uddb9": [
            "RR",
            0
        ],
        "\ud804\uddba": [
            "LR",
            0
        ],
        "\ud804\uddbb": [
            "LRR",
            0
        ],
        "\ud804\uddbc": [
            "E",
            0,
            "\ud804\uddcc"
        ],
        "\ud804\uddbc\ud804\uddcc": [
            "e",
            0
        ],
        "\ud804\uddbd": [
            "ai",
            0
        ],
        "\ud804\uddbe": [
            "O",
            0,
            "\ud804\uddcc"
        ],
        "\ud804\uddbe\ud804\uddcc": [
            "o",
            0
        ],
        "\ud804\uddbf": [
            "au",
            0
        ],
        "\ud804\uddc0": [
            "",
            2
        ],
        "\ud804\uddc1": [
            "''",
            2
        ],
        "\ud804\uddc4": [
            "AUM",
            2
        ],
        "\ud804\uddc5": [
            ".",
            2
        ],
        "\ud804\uddc6": [
            "Q",
            2
        ],
        "\ud804\uddca": [
            ".z",
            2
        ],
        "\ud804\uddcb": [
            "a",
            0,
            "\ud804\uddb3\ud804\uddb6\ud804\uddb7"
        ],
        "\ud804\uddcb\ud804\uddb3": [
            "A",
            0,
            "",
            5
        ],
        "\ud804\uddcb\ud804\uddb6": [
            "u",
            0,
            "",
            13
        ],
        "\ud804\uddcb\ud804\uddb7": [
            "U",
            0,
            "",
            17
        ],
        "\ud804\uddd0": [
            ".0",
            2
        ],
        "\ud804\uddd1": [
            ".1",
            2
        ],
        "\ud804\uddd2": [
            ".2",
            2
        ],
        "\ud804\uddd3": [
            ".3",
            2
        ],
        "\ud804\uddd4": [
            ".4",
            2
        ],
        "\ud804\uddd5": [
            ".5",
            2
        ],
        "\ud804\uddd6": [
            ".6",
            2
        ],
        "\ud804\uddd7": [
            ".7",
            2
        ],
        "\ud804\uddd8": [
            ".8",
            2
        ],
        "\ud804\uddd9": [
            ".9",
            2
        ],
        "\ud804\uddda": [
            ".k",
            2
        ]
    },
    "kram": [
        "\ud804\uddc4",
        "\ud804\udd83",
        "\ud804\udd83\ud804\uddcb",
        "\ud804\uddcb",
        "\ud804\udd84",
        "\ud804\uddb3",
        "\ud804\udd83\ud804\uddcb\ud804\uddb3",
        "\ud804\uddcb\ud804\uddb3",
        "\ud804\udd85",
        "\ud804\uddb4",
        "\ud804\udd86",
        "\ud804\uddb5",
        "\ud804\udd87",
        "\ud804\uddb6",
        "\ud804\udd83\ud804\uddcb\ud804\uddb6",
        "\ud804\uddcb\ud804\uddb6",
        "\ud804\udd88",
        "\ud804\uddb7",
        "\ud804\udd83\ud804\uddcb\ud804\uddb7",
        "\ud804\uddcb\ud804\uddb7",
        "\ud804\udd8d",
        "\ud804\uddbc",
        "\ud804\udd8d\ud804\uddcc",
        "\ud804\uddbc\ud804\uddcc",
        "\ud804\udd8e",
        "\ud804\uddbd",
        "\ud804\udd8e",
        "\ud804\uddbd",
        "\ud804\udd8f",
        "\ud804\uddbe",
        "\ud804\udd8f\ud804\uddcc",
        "\ud804\uddbe\ud804\uddcc",
        "\ud804\udd90",
        "\ud804\uddbf",
        "\ud804\udd90",
        "\ud804\uddbf",
        "\ud804\udd89",
        "\ud804\uddb8",
        "\ud804\udd8a",
        "\ud804\uddb9",
        "\ud804\udd8b",
        "\ud804\uddba",
        "\ud804\udd8c",
        "\ud804\uddbb",
        "\ud804\udd81",
        "\ud804\udd80",
        "\ud804\udd82",
        "\ud804\uddc1",
        "\ud804\uddc0",
        "\ud804\uddca",
        "\ud804\uddc6",
        "\ud804\udd91",
        "\ud804\udd91",
        "\ud804\udd92",
        "\ud804\udd92",
        "\ud804\udd93",
        "\ud804\udd93",
        "\ud804\udd93",
        "\ud804\udd94",
        "\ud804\udd95",
        "\ud804\udd96",
        "\ud804\udd96\ud804\uddca",
        "\ud804\udd97",
        "\ud804\udd97\ud804\uddca",
        "\ud804\udd98",
        "\ud804\udd98",
        "\ud804\udd98",
        "\ud804\udd99",
        "\ud804\udd9a",
        "\ud804\udda0",
        "\ud804\udda1",
        "\ud804\udda2",
        "\ud804\udda3",
        "\ud804\udda4",
        "\ud804\udda4\ud804\uddca",
        "\ud804\udd9b",
        "\ud804\udd9c",
        "\ud804\udd9d",
        "\ud804\udd9d\ud804\uddca",
        "\ud804\udd9d",
        "\ud804\udd9e",
        "\ud804\udd9e\ud804\uddca",
        "\ud804\udd9f",
        "\ud804\udda5",
        "\ud804\udda6",
        "\ud804\udda6",
        "\ud804\udda7",
        "\ud804\udda7",
        "\ud804\udda8",
        "\ud804\udda9",
        "\ud804\uddaa",
        "\ud804\uddaa",
        "\ud804\uddae",
        "\ud804\uddab",
        "\ud804\uddab\ud804\uddca",
        "\ud804\uddac",
        "\ud804\uddad",
        "\ud804\uddad\ud804\uddca",
        "\ud804\uddb2",
        "\ud804\uddb1",
        "\ud804\uddaf",
        "\ud804\uddb0",
        "\u2193",
        "\u2191",
        "\u2191\u2191",
        "\u2191\u2191\u2191",
        "\ud804\uddd0",
        "\ud804\uddd1",
        "\ud804\uddd2",
        "\ud804\uddd3",
        "\ud804\uddd4",
        "\ud804\uddd5",
        "\ud804\uddd6",
        "\ud804\uddd7",
        "\ud804\uddd8",
        "\ud804\uddd9"
    ]
}